eclx/__init__.py
eclx/_ecl_file.py
eclx/_eclascii.py
eclx/_ecldeck.py
eclx/_eclmaps.py
eclx/_errors.py
eclx/_grid.py
eclx/_init.py
eclx/_rst.py
eclx/_sum.py
eclx/_utils.py
eclx/_version.py
eclx/cli.py
eclx/ecl_grammar.lark
eclx-0.2.1.dist-info/LICENSE
eclx-0.2.1.dist-info/METADATA
eclx-0.2.1.dist-info/WHEEL
eclx-0.2.1.dist-info/entry_points.txt
eclx-0.2.1.dist-info/top_level.txt
eclx-0.2.1.dist-info/RECORD
