Metadata-Version: 2.1
Name: eclx
Version: 0.2.1
Summary: Tools for extracting information from Eclipse run decks and results.
Home-page: https://github.com/trhallam/eclx
Author-email: trhallam@gmail.com
License: MIT
Platform: UNKNOWN
Requires-Python: >=3.8
License-File: LICENSE
Requires-Dist: ecl (>2.10)
Requires-Dist: click (>=8.0)
Requires-Dist: tqdm
Requires-Dist: numpy
Requires-Dist: pandas
Requires-Dist: more-itertools
Requires-Dist: loguru
Requires-Dist: dataicer (>=0.2)
Requires-Dist: lark
Requires-Dist: tables
Provides-Extra: docs
Requires-Dist: jupytext ; extra == 'docs'
Provides-Extra: test
Requires-Dist: pytest ; extra == 'test'
Requires-Dist: pytest-cov ; extra == 'test'
Requires-Dist: pandas ; extra == 'test'
Requires-Dist: numpy ; extra == 'test'
Requires-Dist: xarray ; extra == 'test'
